ruuvibot/__init__.py
ruuvibot/dbdata/heatcontrol.sqlite
ruuvibot/ruuvibot.py
ruuvibot/settings.example.json
ruuvibot-0.7.32.dist-info/entry_points.txt
ruuvibot-0.7.32.dist-info/WHEEL
ruuvibot-0.7.32.dist-info/METADATA
ruuvibot-0.7.32.dist-info/RECORD
