Metadata-Version: 2.1
Name: ruuvibot
Version: 0.7.32
Summary: Telegram bot to read ruuvitag data and log data to database
Author: Rami Rahikkala
Author-email: rami.rahikkala@gmail.com
Requires-Python: >=3.9,<4.0
Classifier: Programming Language :: Python :: 3
Classifier: Programming Language :: Python :: 3.9
Classifier: Programming Language :: Python :: 3.10
Classifier: Programming Language :: Python :: 3.11
Requires-Dist: pexpect (>=4.8.0,<5.0.0)
Requires-Dist: python-telegram-bot[job-queue] (>=20.0,<21.0)
Requires-Dist: ruuvitag-sensor (>=2.0.0,<3.0.0)
Requires-Dist: schedule (>=1.1.0,<2.0.0)
